rwmem/__init__.py
rwmem/rwmem.py
rwmem-0.0.7.dist-info/LICENSE
rwmem-0.0.7.dist-info/METADATA
rwmem-0.0.7.dist-info/WHEEL
rwmem-0.0.7.dist-info/top_level.txt
rwmem-0.0.7.dist-info/RECORD
