Metadata-Version: 2.1
Name: rwmem
Version: 0.0.7
Summary: A Simple Read/Write Memory module for Windows python
Home-page: https://github.com/Oseid/rwmem
Author: Oseid Aldary
Author-email: oseid.eng@gmail.com
License: MIT
Platform: UNKNOWN
Classifier: License :: OSI Approved :: MIT License
Classifier: Operating System :: Microsoft :: Windows
Classifier: Programming Language :: Python :: 2.7
Classifier: Programming Language :: Python :: 3.7
